youtube_timestamper/__init__.py
youtube_timestamper/_modidx.py
youtube_timestamper/core.py
youtube_timestamper-0.0.1.dist-info/LICENSE
youtube_timestamper-0.0.1.dist-info/METADATA
youtube_timestamper-0.0.1.dist-info/WHEEL
youtube_timestamper-0.0.1.dist-info/entry_points.txt
youtube_timestamper-0.0.1.dist-info/top_level.txt
youtube_timestamper-0.0.1.dist-info/RECORD
