Metadata-Version: 2.1
Name: youtube-timestamper
Version: 0.0.1
Summary: A python library to automatically create timestamps for youtube interview videos using NLP.
Home-page: https://github.com/ilangurudev/youtube-timestamper/
Author: Guru Ilangovan
Author-email: ilangurudev@gmail.com
License: Apache Software License 2.0
Keywords: nbdev
Platform: UNKNOWN
Classifier: Development Status :: 3 - Alpha
Classifier: Intended Audience :: Developers
Classifier: Natural Language :: English
Classifier: Programming Language :: Python :: 3.7
Classifier: Programming Language :: Python :: 3.8
Classifier: Programming Language :: Python :: 3.9
Classifier: Programming Language :: Python :: 3.10
Classifier: License :: OSI Approved :: Apache Software License
Requires-Python: >=3.7
License-File: LICENSE
Requires-Dist: fastcore
Requires-Dist: youtube-transcript-api
Requires-Dist: deepmultilingualpunctuation
Requires-Dist: spacy
Requires-Dist: sentencepiece
Requires-Dist: protobuf (==3.20)
Provides-Extra: dev
Requires-Dist: nb-black ; extra == 'dev'
Requires-Dist: nbdev ; extra == 'dev'
